yxcompgen/__init__.py
yxcompgen/cli.py
yxcompgen/versions.py
yxcompgen/api/PAML_tools.py
yxcompgen/api/__init__.py
yxcompgen/api/dlcpar.py
yxcompgen/api/orthofinder.py
yxcompgen/api/orthofinder_tree_resolve/__init__.py
yxcompgen/api/orthofinder_tree_resolve/main.py
yxcompgen/api/orthofinder_tree_resolve/newick.py
yxcompgen/api/orthofinder_tree_resolve/resolve.py
yxcompgen/api/orthofinder_tree_resolve/tree.py
yxcompgen/api/orthofinder_tree_resolve/trees2ologs_of.py
yxcompgen/src/__init__.py
yxcompgen/src/orthotools.py
yxcompgen/src/pipeline.py
yxcompgen/src/synteny_block.py
yxcompgen/src/utils.py
yxcompgen-0.0.1.dist-info/LICENSE
yxcompgen-0.0.1.dist-info/METADATA
yxcompgen-0.0.1.dist-info/WHEEL
yxcompgen-0.0.1.dist-info/top_level.txt
yxcompgen-0.0.1.dist-info/RECORD
