Metadata-Version: 2.1
Name: yxcompgen
Version: 0.0.1
Summary: Xu Yuxing's personal comparative genomics tools
Home-page: https://github.com/SouthernCD/yxcompgen
Author: Yuxing Xu
Author-email: xuyuxing@mail.kib.ac.cn
Requires-Python: >=3.5
License-File: LICENSE
Requires-Dist: yxutil
Requires-Dist: yxseq
Requires-Dist: yxmath
Requires-Dist: yxtree
Requires-Dist: yxalign
Requires-Dist: matplotlib >=3.5.0
Requires-Dist: pandas >=1.0.1
Requires-Dist: numpy >=1.18.1
Requires-Dist: pyfaidx >=0.5.5.2
Requires-Dist: interlap >=0.2.6
Requires-Dist: biopython <=1.80
Requires-Dist: bcbio-gff >=0.6.6
Requires-Dist: tables
